{
  "trackSegments": [
    {
      "points": [
        {
          "longitude": -2.1249156475861404,
          "latitude": 52.58407021643043
        },
        {
          "longitude": -2.1230702878459597,
          "latitude": 52.583998509524164
        },
        {
          "longitude": -2.12288253322123,
          "latitude": 52.583978953074826
        },
        {
          "longitude": -2.12252848164315,
          "latitude": 52.58389746777532
        },
        {
          "longitude": -2.1209567072132764,
          "latitude": 52.583349882633186
        },
        {
          "longitude": -2.120023298507466,
          "latitude": 52.582864221038896
        },
        {
          "longitude": -2.118805575655673,
          "latitude": 52.58215690560195
        },
        {
          "longitude": -2.1177648785928738,
          "latitude": 52.58143654036137
        },
        {
          "longitude": -2.1173249963292156,
          "latitude": 52.58118881021277
        },
        {
          "longitude": -2.1164559606376034,
          "latitude": 52.580823731652515
        },
        {
          "longitude": -2.115855145838494,
          "latitude": 52.58063141225967
        },
        {
          "longitude": -2.1143748347329243,
          "latitude": 52.580269588742155
        },
        {
          "longitude": -2.1135004346234756,
          "latitude": 52.58003163110724
        },
        {
          "longitude": -2.112175423414664,
          "latitude": 52.57953615353086
        },
        {
          "longitude": -2.111799914165205,
          "latitude": 52.579285152884744
        },
        {
          "longitude": -2.1110971754269436,
          "latitude": 52.57888746060702
        },
        {
          "longitude": -2.1100779360355544,
          "latitude": 52.57833981287732
        },
        {
          "longitude": -2.108023363999234,
          "latitude": 52.577316214849326
        },
        {
          "longitude": -2.107508379885671,
          "latitude": 52.57704564195031
        },
        {
          "longitude": -2.1068539209080672,
          "latitude": 52.57662184971636
        },
        {
          "longitude": -2.1052875108960625,
          "latitude": 52.57571557257709
        },
        {
          "longitude": -2.1046545095898064,
          "latitude": 52.57530806775798
        },
        {
          "longitude": -2.103721100884026,
          "latitude": 52.57492337973354
        },
        {
          "longitude": -2.102331716661015,
          "latitude": 52.5745321681116
        },
        {
          "longitude": -2.1015914269978015,
          "latitude": 52.57433004073933
        },
        {
          "longitude": -2.100947696855872,
          "latitude": 52.57408879072039
        },
        {
          "longitude": -2.100507814592213,
          "latitude": 52.57380189707815
        },
        {
          "longitude": -2.099687058661259,
          "latitude": 52.57334873170538
        },
        {
          "longitude": -2.099134523622775,
          "latitude": 52.57300640943374
        },
        {
          "longitude": -2.0980616400528915,
          "latitude": 52.57195334416645
        },
        {
          "longitude": -2.097058762135933,
          "latitude": 52.5709295970323
        },
        {
          "longitude": -2.096640337543685,
          "latitude": 52.57061659950732
        },
        {
          "longitude": -2.0962809215477676,
          "latitude": 52.57041119366745
        },
        {
          "longitude": -2.0962255,
          "latitude": 52.5703593
        },
        {
          "longitude": -2.0961182,
          "latitude": 52.570308
        },
        {
          "longitude": -2.0959921,
          "latitude": 52.5702509
        },
        {
          "longitude": -2.0958728,
          "latitude": 52.5701963
        },
        {
          "longitude": -2.0957735,
          "latitude": 52.5701563
        },
        {
          "longitude": -2.0956703,
          "latitude": 52.5701164
        },
        {
          "longitude": -2.0955791,
          "latitude": 52.5700846
        },
        {
          "longitude": -2.0954718,
          "latitude": 52.5700471
        },
        {
          "longitude": -2.0954087,
          "latitude": 52.5700251
        },
        {
          "longitude": -2.0953377,
          "latitude": 52.5700023
        },
        {
          "longitude": -2.0951486,
          "latitude": 52.5699477
        },
        {
          "longitude": -2.0950694,
          "latitude": 52.5699257
        },
        {
          "longitude": -2.0949809,
          "latitude": 52.5699037
        },
        {
          "longitude": -2.0948696,
          "latitude": 52.5698776
        },
        {
          "longitude": -2.0947596,
          "latitude": 52.5698531
        },
        {
          "longitude": -2.0946564,
          "latitude": 52.5698311
        },
        {
          "longitude": -2.0945705,
          "latitude": 52.5698148
        },
        {
          "longitude": -2.0944914,
          "latitude": 52.5698018
        },
        {
          "longitude": -2.0943895,
          "latitude": 52.5697847
        },
        {
          "longitude": -2.094297,
          "latitude": 52.5697692
        },
        {
          "longitude": -2.0942272,
          "latitude": 52.5697586
        },
        {
          "longitude": -2.0938785,
          "latitude": 52.569708
        },
        {
          "longitude": -2.0935258,
          "latitude": 52.5696608
        },
        {
          "longitude": -2.0931624,
          "latitude": 52.5696094
        },
        {
          "longitude": -2.0928217,
          "latitude": 52.5695613
        },
        {
          "longitude": -2.092414,
          "latitude": 52.5695051
        },
        {
          "longitude": -2.0920707,
          "latitude": 52.569457
        },
        {
          "longitude": -2.0916738,
          "latitude": 52.5694007
        },
        {
          "longitude": -2.0913251,
          "latitude": 52.5693535
        },
        {
          "longitude": -2.090916,
          "latitude": 52.5692964
        },
        {
          "longitude": -2.0905727,
          "latitude": 52.5692508
        },
        {
          "longitude": -2.0901838,
          "latitude": 52.5691978
        },
        {
          "longitude": -2.0898284,
          "latitude": 52.5691513
        },
        {
          "longitude": -2.0893872,
          "latitude": 52.5690918
        },
        {
          "longitude": -2.0888641,
          "latitude": 52.5690217
        },
        {
          "longitude": -2.0882566,
          "latitude": 52.5689394
        },
        {
          "longitude": -2.0877926,
          "latitude": 52.5688733
        },
        {
          "longitude": -2.087515,
          "latitude": 52.5688399
        },
        {
          "longitude": -2.0871623,
          "latitude": 52.5687975
        },
        {
          "longitude": -2.086823,
          "latitude": 52.5687535
        },
        {
          "longitude": -2.0864394,
          "latitude": 52.5687014
        },
        {
          "longitude": -2.0860545,
          "latitude": 52.5686492
        },
        {
          "longitude": -2.0856884,
          "latitude": 52.5685995
        },
        {
          "longitude": -2.0853102,
          "latitude": 52.5685481
        },
        {
          "longitude": -2.0849656,
          "latitude": 52.5685008
        },
        {
          "longitude": -2.0845927,
          "latitude": 52.5684503
        },
        {
          "longitude": -2.0841917,
          "latitude": 52.5683957
        },
        {
          "longitude": -2.0836003,
          "latitude": 52.5683182
        },
        {
          "longitude": -2.0831698,
          "latitude": 52.5682587
        },
        {
          "longitude": -2.0827179,
          "latitude": 52.5681984
        },
        {
          "longitude": -2.0822015,
          "latitude": 52.5681275
        },
        {
          "longitude": -2.0818743,
          "latitude": 52.5680827
        },
        {
          "longitude": -2.081706,
          "latitude": 52.5680713
        },
        {
          "longitude": -2.0815576,
          "latitude": 52.5680528
        },
        {
          "longitude": -2.0812573,
          "latitude": 52.5680183
        },
        {
          "longitude": -2.0804911,
          "latitude": 52.567888
        },
        {
          "longitude": -2.0803138,
          "latitude": 52.5678377
        },
        {
          "longitude": -2.0801427,
          "latitude": 52.5678025
        },
        {
          "longitude": -2.0796722,
          "latitude": 52.56768
        },
        {
          "longitude": -2.0794415,
          "latitude": 52.5676197
        },
        {
          "longitude": -2.0792524,
          "latitude": 52.5675675
        },
        {
          "longitude": -2.0790365,
          "latitude": 52.5675039
        },
        {
          "longitude": -2.0788072,
          "latitude": 52.5674338
        },
        {
          "longitude": -2.0785886,
          "latitude": 52.5673653
        },
        {
          "longitude": -2.0783767,
          "latitude": 52.5672952
        },
        {
          "longitude": -2.0782037,
          "latitude": 52.5672349
        },
        {
          "longitude": -2.0780347,
          "latitude": 52.5671713
        },
        {
          "longitude": -2.0778322,
          "latitude": 52.5670922
        },
        {
          "longitude": -2.0776471,
          "latitude": 52.5670213
        },
        {
          "longitude": -2.0774452,
          "latitude": 52.5669345
        },
        {
          "longitude": -2.0772274,
          "latitude": 52.5668404
        },
        {
          "longitude": -2.0770235,
          "latitude": 52.5667491
        },
        {
          "longitude": -2.0768666,
          "latitude": 52.5666765
        },
        {
          "longitude": -2.0767258,
          "latitude": 52.5666064
        },
        {
          "longitude": -2.0763758,
          "latitude": 52.5664271
        },
        {
          "longitude": -2.0761129,
          "latitude": 52.5662974
        },
        {
          "longitude": -2.0759721,
          "latitude": 52.5662225
        },
        {
          "longitude": -2.07583,
          "latitude": 52.5661507
        },
        {
          "longitude": -2.0756784,
          "latitude": 52.5660684
        },
        {
          "longitude": -2.0755617,
          "latitude": 52.5660048
        },
        {
          "longitude": -2.0754932,
          "latitude": 52.5659659
        },
        {
          "longitude": -2.0754316,
          "latitude": 52.5659241
        },
        {
          "longitude": -2.0753069,
          "latitude": 52.5658434
        },
        {
          "longitude": -2.0752077,
          "latitude": 52.5657774
        },
        {
          "longitude": -2.0750964,
          "latitude": 52.5656991
        },
        {
          "longitude": -2.0750025,
          "latitude": 52.5656331
        },
        {
          "longitude": -2.074918,
          "latitude": 52.5655687
        },
        {
          "longitude": -2.0747746,
          "latitude": 52.5654571
        },
        {
          "longitude": -2.0745639,
          "latitude": 52.5652866
        },
        {
          "longitude": -2.0743145,
          "latitude": 52.5650869
        },
        {
          "longitude": -2.0741884,
          "latitude": 52.5649899
        },
        {
          "longitude": -2.0740758,
          "latitude": 52.56491
        },
        {
          "longitude": -2.073998,
          "latitude": 52.5648537
        },
        {
          "longitude": -2.0736882,
          "latitude": 52.5646532
        },
        {
          "longitude": -2.0735648,
          "latitude": 52.5645766
        },
        {
          "longitude": -2.0733288,
          "latitude": 52.5644478
        },
        {
          "longitude": -2.0730834,
          "latitude": 52.5643108
        },
        {
          "longitude": -2.0727977,
          "latitude": 52.5641478
        },
        {
          "longitude": -2.0725469,
          "latitude": 52.564001
        },
        {
          "longitude": -2.0722532,
          "latitude": 52.56382
        },
        {
          "longitude": -2.0719984,
          "latitude": 52.5636578
        },
        {
          "longitude": -2.0717825,
          "latitude": 52.5635184
        },
        {
          "longitude": -2.0717825,
          "latitude": 52.5635184
        },
        {
          "longitude": -2.0716417,
          "latitude": 52.5634279
        },
        {
          "longitude": -2.0716417,
          "latitude": 52.5634279
        },
        {
          "longitude": -2.0714821,
          "latitude": 52.5633276
        },
        {
          "longitude": -2.0712273,
          "latitude": 52.5631727
        },
        {
          "longitude": -2.0709617,
          "latitude": 52.5630113
        },
        {
          "longitude": -2.0707431,
          "latitude": 52.5628793
        },
        {
          "longitude": -2.0704414,
          "latitude": 52.5626909
        },
        {
          "longitude": -2.0701812,
          "latitude": 52.5625312
        },
        {
          "longitude": -2.0699304,
          "latitude": 52.5623746
        },
        {
          "longitude": -2.0696971,
          "latitude": 52.5622271
        },
        {
          "longitude": -2.0694275,
          "latitude": 52.5620591
        },
        {
          "longitude": -2.0691848,
          "latitude": 52.5619067
        },
        {
          "longitude": -2.0688951,
          "latitude": 52.5617232
        },
        {
          "longitude": -2.0686859,
          "latitude": 52.5615895
        },
        {
          "longitude": -2.0684297,
          "latitude": 52.5614248
        },
        {
          "longitude": -2.0682621,
          "latitude": 52.5613156
        },
        {
          "longitude": -2.0680328,
          "latitude": 52.5611721
        },
        {
          "longitude": -2.067782,
          "latitude": 52.5610229
        },
        {
          "longitude": -2.0674856,
          "latitude": 52.5608509
        },
        {
          "longitude": -2.0673783,
          "latitude": 52.5607897
        },
        {
          "longitude": -2.067271,
          "latitude": 52.560731
        },
        {
          "longitude": -2.0671785,
          "latitude": 52.5606829
        },
        {
          "longitude": -2.0670886,
          "latitude": 52.5606397
        },
        {
          "longitude": -2.0669994,
          "latitude": 52.5605977
        },
        {
          "longitude": -2.0667936,
          "latitude": 52.5604971
        },
        {
          "longitude": -2.0667037,
          "latitude": 52.5604506
        },
        {
          "longitude": -2.0664436,
          "latitude": 52.560312
        },
        {
          "longitude": -2.0661797,
          "latitude": 52.5601884
        },
        {
          "longitude": -2.0659122,
          "latitude": 52.5600604
        },
        {
          "longitude": -2.0656599,
          "latitude": 52.559926
        },
        {
          "longitude": -2.0652413,
          "latitude": 52.5596979
        },
        {
          "longitude": -2.064849,
          "latitude": 52.5594861
        },
        {
          "longitude": -2.0645513,
          "latitude": 52.5593344
        },
        {
          "longitude": -2.0642616,
          "latitude": 52.5591926
        },
        {
          "longitude": -2.0638901,
          "latitude": 52.5590059
        },
        {
          "longitude": -2.0636259,
          "latitude": 52.5588746
        },
        {
          "longitude": -2.0633349,
          "latitude": 52.558727
        },
        {
          "longitude": -2.0630264,
          "latitude": 52.5585713
        },
        {
          "longitude": -2.0627126,
          "latitude": 52.5584156
        },
        {
          "longitude": -2.062384,
          "latitude": 52.5582492
        },
        {
          "longitude": -2.0621064,
          "latitude": 52.5581082
        },
        {
          "longitude": -2.0617591,
          "latitude": 52.5579313
        },
        {
          "longitude": -2.0614922,
          "latitude": 52.5577967
        },
        {
          "longitude": -2.061118,
          "latitude": 52.5576076
        },
        {
          "longitude": -2.060772,
          "latitude": 52.5574355
        },
        {
          "longitude": -2.0604019,
          "latitude": 52.5572521
        },
        {
          "longitude": -2.0601498,
          "latitude": 52.5571273
        },
        {
          "longitude": -2.0598561,
          "latitude": 52.5569781
        },
        {
          "longitude": -2.0591386,
          "latitude": 52.5566202
        },
        {
          "longitude": -2.0588543,
          "latitude": 52.5564767
        },
        {
          "longitude": -2.0585833,
          "latitude": 52.5563397
        },
        {
          "longitude": -2.0582816,
          "latitude": 52.5561905
        },
        {
          "longitude": -2.0579496,
          "latitude": 52.5560213
        },
        {
          "longitude": -2.0577515,
          "latitude": 52.5559222
        },
        {
          "longitude": -2.0576419,
          "latitude": 52.5558668
        },
        {
          "longitude": -2.0573455,
          "latitude": 52.5557184
        },
        {
          "longitude": -2.0570867,
          "latitude": 52.5555887
        },
        {
          "longitude": -2.0567702,
          "latitude": 52.5554297
        },
        {
          "longitude": -2.0565006,
          "latitude": 52.555296
        },
        {
          "longitude": -2.0562391,
          "latitude": 52.5551639
        },
        {
          "longitude": -2.0559695,
          "latitude": 52.5550261
        },
        {
          "longitude": -2.0556276,
          "latitude": 52.5548524
        },
        {
          "longitude": -2.0553258,
          "latitude": 52.5546983
        },
        {
          "longitude": -2.0550348,
          "latitude": 52.5545483
        },
        {
          "longitude": -2.0547263,
          "latitude": 52.5543877
        },
        {
          "longitude": -2.0544206,
          "latitude": 52.5542311
        },
        {
          "longitude": -2.0541121,
          "latitude": 52.5540721
        },
        {
          "longitude": -2.0538425,
          "latitude": 52.5539335
        },
        {
          "longitude": -2.0535395,
          "latitude": 52.5537761
        },
        {
          "longitude": -2.0532632,
          "latitude": 52.5536334
        },
        {
          "longitude": -2.0529199,
          "latitude": 52.5534548
        },
        {
          "longitude": -2.0525403,
          "latitude": 52.55326
        },
        {
          "longitude": -2.0522279,
          "latitude": 52.5530969
        },
        {
          "longitude": -2.051969,
          "latitude": 52.5529623
        },
        {
          "longitude": -2.0516713,
          "latitude": 52.5528025
        },
        {
          "longitude": -2.0515144,
          "latitude": 52.5527226
        },
        {
          "longitude": -2.0514178,
          "latitude": 52.5526753
        },
        {
          "longitude": -2.0513253,
          "latitude": 52.5526321
        },
        {
          "longitude": -2.0512153,
          "latitude": 52.552584
        },
        {
          "longitude": -2.0510906,
          "latitude": 52.5525269
        },
        {
          "longitude": -2.0509981,
          "latitude": 52.5524853
        },
        {
          "longitude": -2.0509981,
          "latitude": 52.5524853
        },
        {
          "longitude": -2.0506439,
          "latitude": 52.5523496
        },
        {
          "longitude": -2.0506439,
          "latitude": 52.5523496
        },
        {
          "longitude": -2.0502913,
          "latitude": 52.5522146
        },
        {
          "longitude": -2.0501202,
          "latitude": 52.5521489
        },
        {
          "longitude": -2.0499882,
          "latitude": 52.552102
        },
        {
          "longitude": -2.0498139,
          "latitude": 52.5520425
        },
        {
          "longitude": -2.0496529,
          "latitude": 52.5519887
        },
        {
          "longitude": -2.0494939,
          "latitude": 52.5519385
        },
        {
          "longitude": -2.0493633,
          "latitude": 52.551899
        },
        {
          "longitude": -2.0492144,
          "latitude": 52.5518566
        },
        {
          "longitude": -2.0491004,
          "latitude": 52.5518248
        },
        {
          "longitude": -2.0489495,
          "latitude": 52.5517828
        },
        {
          "longitude": -2.0489495,
          "latitude": 52.5517828
        },
        {
          "longitude": -2.048716,
          "latitude": 52.551719
        },
        {
          "longitude": -2.048716,
          "latitude": 52.551719
        },
        {
          "longitude": -2.0486592,
          "latitude": 52.5517041
        },
        {
          "longitude": -2.0486592,
          "latitude": 52.5517041
        },
        {
          "longitude": -2.0483413,
          "latitude": 52.5516185
        },
        {
          "longitude": -2.0483413,
          "latitude": 52.5516185
        },
        {
          "longitude": -2.0479149,
          "latitude": 52.5515019
        },
        {
          "longitude": -2.0476446,
          "latitude": 52.5514321
        },
        {
          "longitude": -2.0475058,
          "latitude": 52.5513943
        },
        {
          "longitude": -2.0473978,
          "latitude": 52.5513669
        },
        {
          "longitude": -2.0472805,
          "latitude": 52.5513396
        },
        {
          "longitude": -2.0471719,
          "latitude": 52.5513144
        },
        {
          "longitude": -2.0470458,
          "latitude": 52.5512883
        },
        {
          "longitude": -2.0469171,
          "latitude": 52.5512613
        },
        {
          "longitude": -2.0467857,
          "latitude": 52.5512353
        },
        {
          "longitude": -2.0466596,
          "latitude": 52.5512108
        },
        {
          "longitude": -2.0465443,
          "latitude": 52.5511896
        },
        {
          "longitude": -2.0464343,
          "latitude": 52.55117
        },
        {
          "longitude": -2.0462666,
          "latitude": 52.5511423
        },
        {
          "longitude": -2.0461446,
          "latitude": 52.5511235
        },
        {
          "longitude": -2.0460333,
          "latitude": 52.5511064
        },
        {
          "longitude": -2.0459247,
          "latitude": 52.5510917
        },
        {
          "longitude": -2.0458066,
          "latitude": 52.5510754
        },
        {
          "longitude": -2.0457154,
          "latitude": 52.5510632
        },
        {
          "longitude": -2.0453466,
          "latitude": 52.5510216
        },
        {
          "longitude": -2.0449738,
          "latitude": 52.5509841
        },
        {
          "longitude": -2.0445903,
          "latitude": 52.5509449
        },
        {
          "longitude": -2.0441893,
          "latitude": 52.5509058
        },
        {
          "longitude": -2.0437843,
          "latitude": 52.550865
        },
        {
          "longitude": -2.0434865,
          "latitude": 52.5508381
        },
        {
          "longitude": -2.043166,
          "latitude": 52.5508079
        },
        {
          "longitude": -2.0427288,
          "latitude": 52.5507664
        },
        {
          "longitude": -2.0423681,
          "latitude": 52.5507297
        },
        {
          "longitude": -2.0419912,
          "latitude": 52.5506922
        },
        {
          "longitude": -2.0416211,
          "latitude": 52.5506571
        },
        {
          "longitude": -2.0412241,
          "latitude": 52.5506171
        },
        {
          "longitude": -2.040756,
          "latitude": 52.5505706
        },
        {
          "longitude": -2.0405173,
          "latitude": 52.5505454
        },
        {
          "longitude": -2.0402103,
          "latitude": 52.5505136
        },
        {
          "longitude": -2.0398857,
          "latitude": 52.5504793
        },
        {
          "longitude": -2.0397543,
          "latitude": 52.5504638
        },
        {
          "longitude": -2.0396162,
          "latitude": 52.5504467
        },
        {
          "longitude": -2.0395102,
          "latitude": 52.550432
        },
        {
          "longitude": -2.0393788,
          "latitude": 52.5504141
        },
        {
          "longitude": -2.0390247,
          "latitude": 52.5503643
        },
        {
          "longitude": -2.0386452,
          "latitude": 52.5503081
        },
        {
          "longitude": -2.038377,
          "latitude": 52.5502681
        },
        {
          "longitude": -2.038271,
          "latitude": 52.5502551
        },
        {
          "longitude": -2.0381329,
          "latitude": 52.5502404
        },
        {
          "longitude": -2.0376902,
          "latitude": 52.5501979
        },
        {
          "longitude": -2.0376902,
          "latitude": 52.5501979
        },
        {
          "longitude": -2.0372745,
          "latitude": 52.5501563
        },
        {
          "longitude": -2.0372745,
          "latitude": 52.5501563
        },
        {
          "longitude": -2.0365798,
          "latitude": 52.5500805
        },
        {
          "longitude": -2.0363263,
          "latitude": 52.5500609
        },
        {
          "longitude": -2.0359951,
          "latitude": 52.5500356
        },
        {
          "longitude": -2.03559,
          "latitude": 52.5500063
        },
        {
          "longitude": -2.0351904,
          "latitude": 52.549972
        },
        {
          "longitude": -2.0349892,
          "latitude": 52.5499525
        },
        {
          "longitude": -2.0345641,
          "latitude": 52.5499101
        },
        {
          "longitude": -2.0342854,
          "latitude": 52.5498834
        },
        {
          "longitude": -2.0340279,
          "latitude": 52.5498588
        },
        {
          "longitude": -2.0333893,
          "latitude": 52.5497967
        },
        {
          "longitude": -2.0328126,
          "latitude": 52.5497412
        },
        {
          "longitude": -2.0323532,
          "latitude": 52.5496994
        },
        {
          "longitude": -2.0316933,
          "latitude": 52.5496353
        },
        {
          "longitude": -2.0312797,
          "latitude": 52.5495945
        },
        {
          "longitude": -2.0308533,
          "latitude": 52.5495521
        },
        {
          "longitude": -2.0306691,
          "latitude": 52.549536
        },
        {
          "longitude": -2.0304483,
          "latitude": 52.5495137
        },
        {
          "longitude": -2.02815281486033,
          "latitude": 52.549284305087646
        },
        {
          "longitude": -2.026682964369577,
          "latitude": 52.54915382536027
        },
        {
          "longitude": -2.024558118459412,
          "latitude": 52.54867104699588
        },
        {
          "longitude": -2.022948793104587,
          "latitude": 52.54795991784053
        },
        {
          "longitude": -2.022154859262879,
          "latitude": 52.547405359585454
        },
        {
          "longitude": -2.021747163506336,
          "latitude": 52.54709871848299
        },
        {
          "longitude": -2.021307281242678,
          "latitude": 52.54658329563278
        },
        {
          "longitude": -2.0191722429386156,
          "latitude": 52.54351673076427
        },
        {
          "longitude": -2.016693881892179,
          "latitude": 52.539973602903636
        },
        {
          "longitude": -2.014805606809178,
          "latitude": 52.53724591740582
        },
        {
          "longitude": -2.013110450768775,
          "latitude": 52.53484436980121
        },
        {
          "longitude": -2.011994651856071,
          "latitude": 52.53265153770395
        },
        {
          "longitude": -2.0107822934221153,
          "latitude": 52.53031990191453
        },
        {
          "longitude": -2.010465792768987,
          "latitude": 52.52971943262449
        },
        {
          "longitude": -2.0104041019637378,
          "latitude": 52.52955870779392
        },
        {
          "longitude": -2.010331682322783,
          "latitude": 52.52939227130882
        },
        {
          "longitude": -2.0102861,
          "latitude": 52.5292693
        },
        {
          "longitude": -2.0102365,
          "latitude": 52.5291486
        },
        {
          "longitude": -2.0101842,
          "latitude": 52.5290099
        },
        {
          "longitude": -2.0100983,
          "latitude": 52.5288092
        },
        {
          "longitude": -2.0100246,
          "latitude": 52.5286321
        },
        {
          "longitude": -2.0099602,
          "latitude": 52.5284616
        },
        {
          "longitude": -2.0098891,
          "latitude": 52.5282919
        },
        {
          "longitude": -2.009802,
          "latitude": 52.5281149
        },
        {
          "longitude": -2.0096893,
          "latitude": 52.5278734
        },
        {
          "longitude": -2.0095109,
          "latitude": 52.527516
        },
        {
          "longitude": -2.0094238,
          "latitude": 52.5273169
        },
        {
          "longitude": -2.0093031,
          "latitude": 52.5270811
        },
        {
          "longitude": -2.0091703,
          "latitude": 52.5267882
        },
        {
          "longitude": -2.0090804,
          "latitude": 52.5265769
        },
        {
          "longitude": -2.0089892,
          "latitude": 52.5263639
        },
        {
          "longitude": -2.0088846,
          "latitude": 52.5261102
        },
        {
          "longitude": -2.0087706,
          "latitude": 52.5258548
        },
        {
          "longitude": -2.0087465,
          "latitude": 52.525792
        },
        {
          "longitude": -2.0087317,
          "latitude": 52.5257454
        },
        {
          "longitude": -2.0087237,
          "latitude": 52.5257055
        },
        {
          "longitude": -2.0086414,
          "latitude": 52.5254566
        },
        {
          "longitude": -2.008613,
          "latitude": 52.5253477
        },
        {
          "longitude": -2.0085611,
          "latitude": 52.525159
        },
        {
          "longitude": -2.0085149,
          "latitude": 52.5249234
        },
        {
          "longitude": -2.0084862,
          "latitude": 52.5248326
        },
        {
          "longitude": -2.0084542,
          "latitude": 52.5247418
        },
        {
          "longitude": -2.008432,
          "latitude": 52.5246543
        },
        {
          "longitude": -2.0084085,
          "latitude": 52.5245999
        },
        {
          "longitude": -2.0083723,
          "latitude": 52.5245354
        },
        {
          "longitude": -2.008198,
          "latitude": 52.5242523
        },
        {
          "longitude": -2.0080666,
          "latitude": 52.5240336
        },
        {
          "longitude": -2.0079941,
          "latitude": 52.523912
        },
        {
          "longitude": -2.0078815,
          "latitude": 52.5237562
        },
        {
          "longitude": -2.0076911,
          "latitude": 52.5235097
        },
        {
          "longitude": -2.0075529,
          "latitude": 52.5233245
        },
        {
          "longitude": -2.0074134,
          "latitude": 52.5231327
        },
        {
          "longitude": -2.0072418,
          "latitude": 52.5229043
        },
        {
          "longitude": -2.0071224,
          "latitude": 52.5227607
        },
        {
          "longitude": -2.0070031,
          "latitude": 52.522617
        },
        {
          "longitude": -2.0068395,
          "latitude": 52.5224392
        },
        {
          "longitude": -2.0066866,
          "latitude": 52.5222849
        },
        {
          "longitude": -2.0065685,
          "latitude": 52.5221682
        },
        {
          "longitude": -2.006413,
          "latitude": 52.5220091
        },
        {
          "longitude": -2.006244,
          "latitude": 52.5218386
        },
        {
          "longitude": -2.0060388,
          "latitude": 52.5216362
        },
        {
          "longitude": -2.0059409,
          "latitude": 52.5215367
        },
        {
          "longitude": -2.0058537,
          "latitude": 52.5214477
        },
        {
          "longitude": -2.0057813,
          "latitude": 52.5213841
        },
        {
          "longitude": -2.005721,
          "latitude": 52.521331
        },
        {
          "longitude": -2.0056606,
          "latitude": 52.5212763
        },
        {
          "longitude": -2.0055976,
          "latitude": 52.5212225
        },
        {
          "longitude": -2.0055131,
          "latitude": 52.5211548
        },
        {
          "longitude": -2.0053683,
          "latitude": 52.5210421
        },
        {
          "longitude": -2.0053012,
          "latitude": 52.5209883
        },
        {
          "longitude": -2.0052355,
          "latitude": 52.5209385
        },
        {
          "longitude": -2.0051564,
          "latitude": 52.5208765
        },
        {
          "longitude": -2.0050839,
          "latitude": 52.5208194
        },
        {
          "longitude": -2.005029,
          "latitude": 52.5207729
        },
        {
          "longitude": -2.0049753,
          "latitude": 52.5207312
        },
        {
          "longitude": -2.0049069,
          "latitude": 52.5206831
        },
        {
          "longitude": -2.0048493,
          "latitude": 52.5206431
        },
        {
          "longitude": -2.0047706,
          "latitude": 52.520593
        },
        {
          "longitude": -2.0042995,
          "latitude": 52.5203036
        },
        {
          "longitude": -2.0040272,
          "latitude": 52.5201551
        },
        {
          "longitude": -2.0039413,
          "latitude": 52.5201102
        },
        {
          "longitude": -2.0038086,
          "latitude": 52.5200384
        },
        {
          "longitude": -2.003712,
          "latitude": 52.519987
        },
        {
          "longitude": -2.0035095,
          "latitude": 52.519885
        },
        {
          "longitude": -2.0033526,
          "latitude": 52.5198099
        },
        {
          "longitude": -2.0032332,
          "latitude": 52.5197553
        },
        {
          "longitude": -2.0031353,
          "latitude": 52.5197145
        },
        {
          "longitude": -2.0029771,
          "latitude": 52.5196516
        },
        {
          "longitude": -2.0028282,
          "latitude": 52.5195872
        },
        {
          "longitude": -2.0026565,
          "latitude": 52.5195227
        },
        {
          "longitude": -2.0024983,
          "latitude": 52.5194639
        },
        {
          "longitude": -2.0023575,
          "latitude": 52.5194133
        },
        {
          "longitude": -2.0021134,
          "latitude": 52.5193268
        },
        {
          "longitude": -2.0019042,
          "latitude": 52.5192501
        },
        {
          "longitude": -2.0017191,
          "latitude": 52.519184
        },
        {
          "longitude": -2.0015327,
          "latitude": 52.5191179
        },
        {
          "longitude": -2.0013463,
          "latitude": 52.51906
        },
        {
          "longitude": -2.0011746,
          "latitude": 52.5190061
        },
        {
          "longitude": -2.001011,
          "latitude": 52.5189572
        },
        {
          "longitude": -2.0008233,
          "latitude": 52.5189049
        },
        {
          "longitude": -2.0005564,
          "latitude": 52.5188323
        },
        {
          "longitude": -2.0002741,
          "latitude": 52.5187566
        },
        {
          "longitude": -1.9996496,
          "latitude": 52.518591
        },
        {
          "longitude": -1.9993735,
          "latitude": 52.5185181
        },
        {
          "longitude": -1.9991201,
          "latitude": 52.5184504
        },
        {
          "longitude": -1.9989189,
          "latitude": 52.5183949
        },
        {
          "longitude": -1.9987419,
          "latitude": 52.5183443
        },
        {
          "longitude": -1.998585,
          "latitude": 52.518297
        },
        {
          "longitude": -1.9984173,
          "latitude": 52.5182447
        },
        {
          "longitude": -1.9982363,
          "latitude": 52.518186
        },
        {
          "longitude": -1.9980955,
          "latitude": 52.5181378
        },
        {
          "longitude": -1.997956,
          "latitude": 52.5180889
        },
        {
          "longitude": -1.9974812,
          "latitude": 52.5179085
        },
        {
          "longitude": -1.9972693,
          "latitude": 52.5178334
        },
        {
          "longitude": -1.9971164,
          "latitude": 52.5177747
        },
        {
          "longitude": -1.9968388,
          "latitude": 52.5176588
        },
        {
          "longitude": -1.996525,
          "latitude": 52.5175217
        },
        {
          "longitude": -1.9961589,
          "latitude": 52.517347
        },
        {
          "longitude": -1.9958142,
          "latitude": 52.5171724
        },
        {
          "longitude": -1.995542,
          "latitude": 52.5170263
        },
        {
          "longitude": -1.995432,
          "latitude": 52.5169676
        },
        {
          "longitude": -1.9953516,
          "latitude": 52.5169243
        },
        {
          "longitude": -1.9952764,
          "latitude": 52.5168827
        },
        {
          "longitude": -1.9951866,
          "latitude": 52.5168321
        },
        {
          "longitude": -1.9951276,
          "latitude": 52.5167962
        },
        {
          "longitude": -1.9950739,
          "latitude": 52.5167619
        },
        {
          "longitude": -1.9950082,
          "latitude": 52.5167178
        },
        {
          "longitude": -1.9949576,
          "latitude": 52.5166831
        },
        {
          "longitude": -1.994938,
          "latitude": 52.5166684
        },
        {
          "longitude": -1.9945001,
          "latitude": 52.5163524
        },
        {
          "longitude": -1.9941714,
          "latitude": 52.5161188
        },
        {
          "longitude": -1.994103,
          "latitude": 52.516069
        },
        {
          "longitude": -1.9940453,
          "latitude": 52.5160241
        },
        {
          "longitude": -1.9939783,
          "latitude": 52.5159744
        },
        {
          "longitude": -1.9939179,
          "latitude": 52.5159262
        },
        {
          "longitude": -1.9937181,
          "latitude": 52.5157663
        },
        {
          "longitude": -1.9935504,
          "latitude": 52.5156316
        },
        {
          "longitude": -1.9934365,
          "latitude": 52.5155394
        },
        {
          "longitude": -1.9933265,
          "latitude": 52.5154537
        },
        {
          "longitude": -1.9932393,
          "latitude": 52.5153827
        },
        {
          "longitude": -1.9931669,
          "latitude": 52.5153223
        },
        {
          "longitude": -1.9930797,
          "latitude": 52.5152513
        },
        {
          "longitude": -1.9930019,
          "latitude": 52.5151909
        },
        {
          "longitude": -1.9929094,
          "latitude": 52.5151215
        },
        {
          "longitude": -1.9928182,
          "latitude": 52.515053
        },
        {
          "longitude": -1.9927471,
          "latitude": 52.5150015
        },
        {
          "longitude": -1.9925781,
          "latitude": 52.5148783
        },
        {
          "longitude": -1.9923019,
          "latitude": 52.5146881
        },
        {
          "longitude": -1.9920565,
          "latitude": 52.5145127
        },
        {
          "longitude": -1.9917011,
          "latitude": 52.5142646
        },
        {
          "longitude": -1.9914664,
          "latitude": 52.5141038
        },
        {
          "longitude": -1.9911405,
          "latitude": 52.5138728
        },
        {
          "longitude": -1.9909085,
          "latitude": 52.5137128
        },
        {
          "longitude": -1.9906563,
          "latitude": 52.5135374
        },
        {
          "longitude": -1.990427,
          "latitude": 52.5133799
        },
        {
          "longitude": -1.9902071,
          "latitude": 52.5132248
        },
        {
          "longitude": -1.9900059,
          "latitude": 52.5130852
        },
        {
          "longitude": -1.9898262,
          "latitude": 52.5129628
        },
        {
          "longitude": -1.9895741,
          "latitude": 52.5127889
        },
        {
          "longitude": -1.9893514,
          "latitude": 52.5126322
        },
        {
          "longitude": -1.989043,
          "latitude": 52.5124143
        },
        {
          "longitude": -1.9886313,
          "latitude": 52.5121278
        },
        {
          "longitude": -1.9884933,
          "latitude": 52.5120298
        },
        {
          "longitude": -1.9883215,
          "latitude": 52.5119115
        },
        {
          "longitude": -1.9880432,
          "latitude": 52.5117185
        },
        {
          "longitude": -1.987946,
          "latitude": 52.511652
        },
        {
          "longitude": -1.9877019,
          "latitude": 52.5114822
        },
        {
          "longitude": -1.9873988,
          "latitude": 52.5112716
        },
        {
          "longitude": -1.9870944,
          "latitude": 52.5110709
        },
        {
          "longitude": -1.9868154,
          "latitude": 52.5108831
        },
        {
          "longitude": -1.9865512,
          "latitude": 52.5107036
        },
        {
          "longitude": -1.9862884,
          "latitude": 52.5105264
        },
        {
          "longitude": -1.9860108,
          "latitude": 52.5103379
        },
        {
          "longitude": -1.9857841,
          "latitude": 52.5101902
        },
        {
          "longitude": -1.9856701,
          "latitude": 52.5101134
        },
        {
          "longitude": -1.9855709,
          "latitude": 52.5100522
        },
        {
          "longitude": -1.9854797,
          "latitude": 52.5099959
        },
        {
          "longitude": -1.9853684,
          "latitude": 52.509929
        },
        {
          "longitude": -1.9852504,
          "latitude": 52.5098612
        },
        {
          "longitude": -1.9851525,
          "latitude": 52.5098057
        },
        {
          "longitude": -1.9850304,
          "latitude": 52.5097363
        },
        {
          "longitude": -1.9849124,
          "latitude": 52.5096735
        },
        {
          "longitude": -1.984781,
          "latitude": 52.5096033
        },
        {
          "longitude": -1.9846549,
          "latitude": 52.5095396
        },
        {
          "longitude": -1.9845409,
          "latitude": 52.5094817
        },
        {
          "longitude": -1.9844229,
          "latitude": 52.5094229
        },
        {
          "longitude": -1.9842928,
          "latitude": 52.5093633
        },
        {
          "longitude": -1.9841654,
          "latitude": 52.5093037
        },
        {
          "longitude": -1.9840299,
          "latitude": 52.5092433
        },
        {
          "longitude": -1.9839146,
          "latitude": 52.5091911
        },
        {
          "longitude": -1.9837824,
          "latitude": 52.5091337
        },
        {
          "longitude": -1.9837295,
          "latitude": 52.5091119
        },
        {
          "longitude": -1.983633,
          "latitude": 52.5090736
        },
        {
          "longitude": -1.9835565,
          "latitude": 52.5090434
        },
        {
          "longitude": -1.9834667,
          "latitude": 52.5090066
        },
        {
          "longitude": -1.9833809,
          "latitude": 52.5089699
        },
        {
          "longitude": -1.9833031,
          "latitude": 52.5089389
        },
        {
          "longitude": -1.9832199,
          "latitude": 52.508907
        },
        {
          "longitude": -1.9831395,
          "latitude": 52.5088777
        },
        {
          "longitude": -1.9830657,
          "latitude": 52.5088515
        },
        {
          "longitude": -1.9829919,
          "latitude": 52.5088262
        },
        {
          "longitude": -1.9829115,
          "latitude": 52.5088009
        },
        {
          "longitude": -1.982847,
          "latitude": 52.5087805
        },
        {
          "longitude": -1.9822397,
          "latitude": 52.5085978
        },
        {
          "longitude": -1.9820733,
          "latitude": 52.5085479
        },
        {
          "longitude": -1.9819512,
          "latitude": 52.5085095
        },
        {
          "longitude": -1.9818399,
          "latitude": 52.5084777
        },
        {
          "longitude": -1.9817367,
          "latitude": 52.5084483
        },
        {
          "longitude": -1.9816388,
          "latitude": 52.5084222
        },
        {
          "longitude": -1.9815502,
          "latitude": 52.5083993
        },
        {
          "longitude": -1.9814617,
          "latitude": 52.5083781
        },
        {
          "longitude": -1.9813518,
          "latitude": 52.5083528
        },
        {
          "longitude": -1.9811962,
          "latitude": 52.5083185
        },
        {
          "longitude": -1.9810044,
          "latitude": 52.5082753
        },
        {
          "longitude": -1.9808167,
          "latitude": 52.5082336
        },
        {
          "longitude": -1.9807053,
          "latitude": 52.5082075
        },
        {
          "longitude": -1.9806074,
          "latitude": 52.5081879
        },
        {
          "longitude": -1.9805002,
          "latitude": 52.5081659
        },
        {
          "longitude": -1.9803848,
          "latitude": 52.5081414
        },
        {
          "longitude": -1.98024,
          "latitude": 52.5081136
        },
        {
          "longitude": -1.9800227,
          "latitude": 52.508078
        },
        {
          "longitude": -1.9797969,
          "latitude": 52.508048
        },
        {
          "longitude": -1.9794688,
          "latitude": 52.5080108
        },
        {
          "longitude": -1.9791081,
          "latitude": 52.5079643
        },
        {
          "longitude": -1.9786897,
          "latitude": 52.5079088
        },
        {
          "longitude": -1.9779467,
          "latitude": 52.5078026
        },
        {
          "longitude": -1.9773687,
          "latitude": 52.5077137
        },
        {
          "longitude": -1.9768765,
          "latitude": 52.5076427
        },
        {
          "longitude": -1.9764245,
          "latitude": 52.5075749
        },
        {
          "longitude": -1.9759485,
          "latitude": 52.5075072
        },
        {
          "longitude": -1.9752229,
          "latitude": 52.5074002
        },
        {
          "longitude": -1.9748246,
          "latitude": 52.5073406
        },
        {
          "longitude": -1.9744384,
          "latitude": 52.5072884
        },
        {
          "longitude": -1.973969,
          "latitude": 52.5072247
        },
        {
          "longitude": -1.9735573,
          "latitude": 52.50717
        },
        {
          "longitude": -1.9731496,
          "latitude": 52.5071145
        },
        {
          "longitude": -1.9726547,
          "latitude": 52.507046
        },
        {
          "longitude": -1.972137,
          "latitude": 52.5069684
        },
        {
          "longitude": -1.9717575,
          "latitude": 52.5069121
        },
        {
          "longitude": -1.9713511,
          "latitude": 52.5068476
        },
        {
          "longitude": -1.9711097,
          "latitude": 52.5068125
        },
        {
          "longitude": -1.9709569,
          "latitude": 52.5067896
        },
        {
          "longitude": -1.9707879,
          "latitude": 52.5067603
        },
        {
          "longitude": -1.9706028,
          "latitude": 52.5067301
        },
        {
          "longitude": -1.9704311,
          "latitude": 52.5067048
        },
        {
          "longitude": -1.9702273,
          "latitude": 52.5066778
        },
        {
          "longitude": -1.9698089,
          "latitude": 52.5066223
        },
        {
          "longitude": -1.9694951,
          "latitude": 52.5065888
        },
        {
          "longitude": -1.9691678,
          "latitude": 52.5065537
        },
        {
          "longitude": -1.9689184,
          "latitude": 52.5065301
        },
        {
          "longitude": -1.9687226,
          "latitude": 52.5065105
        },
        {
          "longitude": -1.9685548,
          "latitude": 52.5064917
        },
        {
          "longitude": -1.9684128,
          "latitude": 52.506477
        },
        {
          "longitude": -1.9682693,
          "latitude": 52.5064582
        },
        {
          "longitude": -1.9681419,
          "latitude": 52.5064419
        },
        {
          "longitude": -1.9679541,
          "latitude": 52.5064158
        },
        {
          "longitude": -1.9677865,
          "latitude": 52.5063897
        },
        {
          "longitude": -1.9676363,
          "latitude": 52.5063652
        },
        {
          "longitude": -1.9674713,
          "latitude": 52.5063366
        },
        {
          "longitude": -1.9673158,
          "latitude": 52.506308
        },
        {
          "longitude": -1.9671548,
          "latitude": 52.506277
        },
        {
          "longitude": -1.9667659,
          "latitude": 52.506197
        },
        {
          "longitude": -1.9663582,
          "latitude": 52.5061105
        },
        {
          "longitude": -1.9659975,
          "latitude": 52.5060321
        },
        {
          "longitude": -1.9657225,
          "latitude": 52.5059693
        },
        {
          "longitude": -1.9655763,
          "latitude": 52.5059358
        },
        {
          "longitude": -1.9654074,
          "latitude": 52.5058917
        },
        {
          "longitude": -1.9650761,
          "latitude": 52.5058003
        },
        {
          "longitude": -1.9647905,
          "latitude": 52.5057219
        },
        {
          "longitude": -1.9646376,
          "latitude": 52.505677
        },
        {
          "longitude": -1.9641186,
          "latitude": 52.505517
        },
        {
          "longitude": -1.963967,
          "latitude": 52.5054681
        },
        {
          "longitude": -1.9638664,
          "latitude": 52.5054362
        },
        {
          "longitude": -1.9637592,
          "latitude": 52.5053995
        },
        {
          "longitude": -1.9636639,
          "latitude": 52.5053644
        },
        {
          "longitude": -1.96344,
          "latitude": 52.5052828
        },
        {
          "longitude": -1.9633085,
          "latitude": 52.5052338
        },
        {
          "longitude": -1.9632106,
          "latitude": 52.5051987
        },
        {
          "longitude": -1.9631382,
          "latitude": 52.5051742
        },
        {
          "longitude": -1.9630806,
          "latitude": 52.5051554
        },
        {
          "longitude": -1.9628566,
          "latitude": 52.505095
        },
        {
          "longitude": -1.96252,
          "latitude": 52.5049954
        },
        {
          "longitude": -1.9621404,
          "latitude": 52.5048811
        },
        {
          "longitude": -1.9617596,
          "latitude": 52.5047652
        },
        {
          "longitude": -1.9614149,
          "latitude": 52.5046599
        },
        {
          "longitude": -1.9609871,
          "latitude": 52.5045317
        },
        {
          "longitude": -1.9605781,
          "latitude": 52.5044085
        },
        {
          "longitude": -1.9601261,
          "latitude": 52.5042672
        },
        {
          "longitude": -1.9596648,
          "latitude": 52.5041236
        },
        {
          "longitude": -1.95919,
          "latitude": 52.5039766
        },
        {
          "longitude": -1.9587099,
          "latitude": 52.503833
        },
        {
          "longitude": -1.9579629,
          "latitude": 52.5036117
        },
        {
          "longitude": -1.9573755,
          "latitude": 52.5034476
        },
        {
          "longitude": -1.9569665,
          "latitude": 52.503335
        },
        {
          "longitude": -1.9565977,
          "latitude": 52.5032321
        },
        {
          "longitude": -1.9561484,
          "latitude": 52.5031121
        },
        {
          "longitude": -1.9556991,
          "latitude": 52.5029921
        },
        {
          "longitude": -1.9553156,
          "latitude": 52.5028876
        },
        {
          "longitude": -1.9548059,
          "latitude": 52.5027521
        },
        {
          "longitude": -1.954307,
          "latitude": 52.502619
        },
        {
          "longitude": -1.9539141,
          "latitude": 52.5025129
        },
        {
          "longitude": -1.9534984,
          "latitude": 52.5024027
        },
        {
          "longitude": -1.9528962,
          "latitude": 52.5022435
        },
        {
          "longitude": -1.9526174,
          "latitude": 52.5021681
        },
        {
          "longitude": -1.9519953,
          "latitude": 52.5020024
        },
        {
          "longitude": -1.9519635,
          "latitude": 52.5019948
        },
        {
          "longitude": -1.9514331,
          "latitude": 52.5018647
        },
        {
          "longitude": -1.9509656,
          "latitude": 52.5017517
        },
        {
          "longitude": -1.9509656,
          "latitude": 52.5017517
        },
        {
          "longitude": -1.9506029,
          "latitude": 52.5016655
        },
        {
          "longitude": -1.9506029,
          "latitude": 52.5016655
        },
        {
          "longitude": -1.9502301,
          "latitude": 52.5015782
        },
        {
          "longitude": -1.9498117,
          "latitude": 52.5014753
        },
        {
          "longitude": -1.9493839,
          "latitude": 52.5013716
        },
        {
          "longitude": -1.9490083,
          "latitude": 52.5012818
        },
        {
          "longitude": -1.9486248,
          "latitude": 52.5011879
        },
        {
          "longitude": -1.9481366,
          "latitude": 52.5010704
        },
        {
          "longitude": -1.9477571,
          "latitude": 52.5009798
        },
        {
          "longitude": -1.9472408,
          "latitude": 52.5008565
        },
        {
          "longitude": -1.9467499,
          "latitude": 52.5007397
        },
        {
          "longitude": -1.9467499,
          "latitude": 52.5007397
        },
        {
          "longitude": -1.9462296,
          "latitude": 52.5006132
        },
        {
          "longitude": -1.9456998,
          "latitude": 52.5004826
        },
        {
          "longitude": -1.945209,
          "latitude": 52.5003601
        },
        {
          "longitude": -1.944643,
          "latitude": 52.5002238
        },
        {
          "longitude": -1.944179,
          "latitude": 52.5001078
        },
        {
          "longitude": -1.9436775,
          "latitude": 52.4999854
        },
        {
          "longitude": -1.9431648,
          "latitude": 52.4998655
        },
        {
          "longitude": -1.9431648,
          "latitude": 52.4998655
        },
        {
          "longitude": -1.9426126,
          "latitude": 52.4997266
        },
        {
          "longitude": -1.9426126,
          "latitude": 52.4997266
        },
        {
          "longitude": -1.942386,
          "latitude": 52.4996711
        },
        {
          "longitude": -1.942386,
          "latitude": 52.4996711
        },
        {
          "longitude": -1.9420252,
          "latitude": 52.4995837
        },
        {
          "longitude": -1.9415451,
          "latitude": 52.4994686
        },
        {
          "longitude": -1.9408799,
          "latitude": 52.4993086
        },
        {
          "longitude": -1.9404306,
          "latitude": 52.4991992
        },
        {
          "longitude": -1.939968,
          "latitude": 52.4990832
        },
        {
          "longitude": -1.9396166,
          "latitude": 52.4990024
        },
        {
          "longitude": -1.9391378,
          "latitude": 52.4988865
        },
        {
          "longitude": -1.9386161,
          "latitude": 52.4987616
        },
        {
          "longitude": -1.9380488,
          "latitude": 52.4986236
        },
        {
          "longitude": -1.9380488,
          "latitude": 52.4986236
        },
        {
          "longitude": -1.9377001,
          "latitude": 52.4985395
        },
        {
          "longitude": -1.9377001,
          "latitude": 52.4985395
        },
        {
          "longitude": -1.9370685,
          "latitude": 52.4983917
        },
        {
          "longitude": -1.9367024,
          "latitude": 52.4983035
        },
        {
          "longitude": -1.9361351,
          "latitude": 52.498168
        },
        {
          "longitude": -1.9356013,
          "latitude": 52.498039
        },
        {
          "longitude": -1.9352365,
          "latitude": 52.4979533
        },
        {
          "longitude": -1.9347967,
          "latitude": 52.4978496
        },
        {
          "longitude": -1.9343836,
          "latitude": 52.49775
        },
        {
          "longitude": -1.9340939,
          "latitude": 52.4976798
        },
        {
          "longitude": -1.9338083,
          "latitude": 52.4976145
        },
        {
          "longitude": -1.9334971,
          "latitude": 52.4975434
        },
        {
          "longitude": -1.9330479,
          "latitude": 52.4974414
        },
        {
          "longitude": -1.9327422,
          "latitude": 52.4973753
        },
        {
          "longitude": -1.9324243,
          "latitude": 52.497305
        },
        {
          "longitude": -1.9321065,
          "latitude": 52.497234
        },
        {
          "longitude": -1.9317336,
          "latitude": 52.4971565
        },
        {
          "longitude": -1.9313252,
          "latitude": 52.497059
        },
        {
          "longitude": -1.9306871,
          "latitude": 52.4968991
        },
        {
          "longitude": -1.930418,
          "latitude": 52.4968299
        },
        {
          "longitude": -1.9302625,
          "latitude": 52.4967882
        },
        {
          "longitude": -1.9301658,
          "latitude": 52.4967621
        },
        {
          "longitude": -1.9300827,
          "latitude": 52.4967367
        },
        {
          "longitude": -1.9300097,
          "latitude": 52.4967143
        },
        {
          "longitude": -1.929889,
          "latitude": 52.4966751
        },
        {
          "longitude": -1.9297883,
          "latitude": 52.4966408
        },
        {
          "longitude": -1.9297286,
          "latitude": 52.4966208
        },
        {
          "longitude": -1.9296522,
          "latitude": 52.496593
        },
        {
          "longitude": -1.9294497,
          "latitude": 52.4965155
        },
        {
          "longitude": -1.9293028,
          "latitude": 52.4964606
        },
        {
          "longitude": -1.9293028,
          "latitude": 52.4964606
        },
        {
          "longitude": -1.9290922,
          "latitude": 52.4963794
        },
        {
          "longitude": -1.9290922,
          "latitude": 52.4963794
        },
        {
          "longitude": -1.9289107,
          "latitude": 52.4963186
        },
        {
          "longitude": -1.9287785,
          "latitude": 52.4962718
        },
        {
          "longitude": -1.9287155,
          "latitude": 52.4962465
        },
        {
          "longitude": -1.9286291,
          "latitude": 52.4962131
        },
        {
          "longitude": -1.9285297,
          "latitude": 52.4961701
        },
        {
          "longitude": -1.9284365,
          "latitude": 52.4961289
        },
        {
          "longitude": -1.9283312,
          "latitude": 52.4960807
        },
        {
          "longitude": -1.9282327,
          "latitude": 52.4960309
        },
        {
          "longitude": -1.9280154,
          "latitude": 52.4959223
        },
        {
          "longitude": -1.927711,
          "latitude": 52.4957558
        },
        {
          "longitude": -1.9275179,
          "latitude": 52.4956484
        },
        {
          "longitude": -1.9273216,
          "latitude": 52.495533
        },
        {
          "longitude": -1.9270659,
          "latitude": 52.4953851
        },
        {
          "longitude": -1.9268614,
          "latitude": 52.4952691
        },
        {
          "longitude": -1.9266012,
          "latitude": 52.4951173
        },
        {
          "longitude": -1.9264061,
          "latitude": 52.4950046
        },
        {
          "longitude": -1.9260648,
          "latitude": 52.4948103
        },
        {
          "longitude": -1.9258026,
          "latitude": 52.49466
        },
        {
          "longitude": -1.9256269,
          "latitude": 52.4945596
        },
        {
          "longitude": -1.9253922,
          "latitude": 52.4944253
        },
        {
          "longitude": -1.925181,
          "latitude": 52.4943044
        },
        {
          "longitude": -1.9249476,
          "latitude": 52.4941664
        },
        {
          "longitude": -1.9247022,
          "latitude": 52.4940215
        },
        {
          "longitude": -1.9245185,
          "latitude": 52.4939129
        },
        {
          "longitude": -1.9242858,
          "latitude": 52.4937737
        },
        {
          "longitude": -1.9240484,
          "latitude": 52.4936316
        },
        {
          "longitude": -1.9238172,
          "latitude": 52.4934958
        },
        {
          "longitude": -1.9236541,
          "latitude": 52.4933964
        },
        {
          "longitude": -1.9234691,
          "latitude": 52.4932878
        },
        {
          "longitude": -1.923294,
          "latitude": 52.4931862
        },
        {
          "longitude": -1.923115,
          "latitude": 52.4930813
        },
        {
          "longitude": -1.9229333,
          "latitude": 52.4929743
        },
        {
          "longitude": -1.9227583,
          "latitude": 52.4928698
        },
        {
          "longitude": -1.9225819,
          "latitude": 52.4927677
        },
        {
          "longitude": -1.9223177,
          "latitude": 52.4926199
        },
        {
          "longitude": -1.9222098,
          "latitude": 52.4925636
        },
        {
          "longitude": -1.9220408,
          "latitude": 52.4924758
        },
        {
          "longitude": -1.9218624,
          "latitude": 52.4923864
        },
        {
          "longitude": -1.9216673,
          "latitude": 52.4922872
        },
        {
          "longitude": -1.921448,
          "latitude": 52.4921757
        },
        {
          "longitude": -1.9212316,
          "latitude": 52.4920652
        },
        {
          "longitude": -1.9210517,
          "latitude": 52.4919761
        },
        {
          "longitude": -1.9208794,
          "latitude": 52.4918932
        },
        {
          "longitude": -1.920705,
          "latitude": 52.4918111
        },
        {
          "longitude": -1.9205233,
          "latitude": 52.4917274
        },
        {
          "longitude": -1.9203465,
          "latitude": 52.4916504
        },
        {
          "longitude": -1.9202115,
          "latitude": 52.4915923
        },
        {
          "longitude": -1.9199929,
          "latitude": 52.4915012
        },
        {
          "longitude": -1.919842,
          "latitude": 52.4914396
        },
        {
          "longitude": -1.9197086,
          "latitude": 52.4913869
        },
        {
          "longitude": -1.9195691,
          "latitude": 52.4913314
        },
        {
          "longitude": -1.9193934,
          "latitude": 52.4912652
        },
        {
          "longitude": -1.9192003,
          "latitude": 52.4911926
        },
        {
          "longitude": -1.9190557,
          "latitude": 52.4911396
        },
        {
          "longitude": -1.9188852,
          "latitude": 52.4910795
        },
        {
          "longitude": -1.9187148,
          "latitude": 52.4910211
        },
        {
          "longitude": -1.9185713,
          "latitude": 52.4909737
        },
        {
          "longitude": -1.9183641,
          "latitude": 52.4909051
        },
        {
          "longitude": -1.9181147,
          "latitude": 52.4908255
        },
        {
          "longitude": -1.917913,
          "latitude": 52.4907648
        },
        {
          "longitude": -1.9176782,
          "latitude": 52.4906944
        },
        {
          "longitude": -1.917528,
          "latitude": 52.4906503
        },
        {
          "longitude": -1.9173992,
          "latitude": 52.4906116
        },
        {
          "longitude": -1.9172519,
          "latitude": 52.4905696
        },
        {
          "longitude": -1.9171062,
          "latitude": 52.4905303
        },
        {
          "longitude": -1.9169593,
          "latitude": 52.4904919
        },
        {
          "longitude": -1.9168246,
          "latitude": 52.4904572
        },
        {
          "longitude": -1.9166918,
          "latitude": 52.4904229
        },
        {
          "longitude": -1.9166918,
          "latitude": 52.4904229
        },
        {
          "longitude": -1.9162734,
          "latitude": 52.4903225
        },
        {
          "longitude": -1.9162734,
          "latitude": 52.4903225
        },
        {
          "longitude": -1.9161641,
          "latitude": 52.4902996
        },
        {
          "longitude": -1.9160145,
          "latitude": 52.4902682
        },
        {
          "longitude": -1.9157465,
          "latitude": 52.4902165
        },
        {
          "longitude": -1.91546,
          "latitude": 52.4901592
        },
        {
          "longitude": -1.9153099,
          "latitude": 52.4901279
        },
        {
          "longitude": -1.915057,
          "latitude": 52.4900722
        },
        {
          "longitude": -1.9147157,
          "latitude": 52.4899987
        },
        {
          "longitude": -1.9143831,
          "latitude": 52.4899256
        },
        {
          "longitude": -1.9140507,
          "latitude": 52.4898531
        },
        {
          "longitude": -1.9138272,
          "latitude": 52.4898048
        },
        {
          "longitude": -1.9134865,
          "latitude": 52.4897309
        },
        {
          "longitude": -1.9133352,
          "latitude": 52.4896979
        },
        {
          "longitude": -1.9132076,
          "latitude": 52.4896713
        },
        {
          "longitude": -1.9130768,
          "latitude": 52.4896431
        },
        {
          "longitude": -1.9129823,
          "latitude": 52.4896243
        },
        {
          "longitude": -1.9128831,
          "latitude": 52.4896043
        },
        {
          "longitude": -1.9127943,
          "latitude": 52.4895874
        },
        {
          "longitude": -1.9127943,
          "latitude": 52.4895874
        },
        {
          "longitude": -1.9107399,
          "latitude": 52.4892148
        },
        {
          "longitude": -1.9107399,
          "latitude": 52.4892148
        },
        {
          "longitude": -1.9106349,
          "latitude": 52.4891912
        },
        {
          "longitude": -1.9105417,
          "latitude": 52.4891708
        },
        {
          "longitude": -1.9104328,
          "latitude": 52.4891445
        },
        {
          "longitude": -1.9103282,
          "latitude": 52.4891176
        },
        {
          "longitude": -1.9101802,
          "latitude": 52.4890793
        },
        {
          "longitude": -1.9100542,
          "latitude": 52.4890467
        },
        {
          "longitude": -1.9099339,
          "latitude": 52.4890139
        },
        {
          "longitude": -1.9098508,
          "latitude": 52.488991
        },
        {
          "longitude": -1.9097595,
          "latitude": 52.4889657
        },
        {
          "longitude": -1.9097595,
          "latitude": 52.4889657
        },
        {
          "longitude": -1.9081538,
          "latitude": 52.4884652
        },
        {
          "longitude": -1.9081538,
          "latitude": 52.4884652
        },
        {
          "longitude": -1.9076071,
          "latitude": 52.4882822
        },
        {
          "longitude": -1.9070519,
          "latitude": 52.4880984
        },
        {
          "longitude": -1.9068224,
          "latitude": 52.4880219
        },
        {
          "longitude": -1.9064028,
          "latitude": 52.487882
        },
        {
          "longitude": -1.9062843,
          "latitude": 52.487843
        },
        {
          "longitude": -1.906203,
          "latitude": 52.4878143
        },
        {
          "longitude": -1.906203,
          "latitude": 52.4878143
        },
        {
          "longitude": -1.905511,
          "latitude": 52.4875374
        },
        {
          "longitude": -1.905511,
          "latitude": 52.4875374
        },
        {
          "longitude": -1.9054024,
          "latitude": 52.4874941
        },
        {
          "longitude": -1.9052683,
          "latitude": 52.4874459
        },
        {
          "longitude": -1.9052079,
          "latitude": 52.4874198
        },
        {
          "longitude": -1.905153,
          "latitude": 52.4873953
        },
        {
          "longitude": -1.9051068,
          "latitude": 52.4873742
        },
        {
          "longitude": -1.9049969,
          "latitude": 52.4873162
        },
        {
          "longitude": -1.9044851,
          "latitude": 52.487027
        },
        {
          "longitude": -1.9042866,
          "latitude": 52.4869192
        },
        {
          "longitude": -1.9041989,
          "latitude": 52.4868687
        },
        {
          "longitude": -1.9041332,
          "latitude": 52.4868287
        },
        {
          "longitude": -1.903958,
          "latitude": 52.4867184
        },
        {
          "longitude": -1.9036777,
          "latitude": 52.4865395
        },
        {
          "longitude": -1.9033071,
          "latitude": 52.4863077
        },
        {
          "longitude": -1.9033071,
          "latitude": 52.4863077
        },
        {
          "longitude": -1.9031783,
          "latitude": 52.4862235
        },
        {
          "longitude": -1.9031783,
          "latitude": 52.4862235
        },
        {
          "longitude": -1.902902,
          "latitude": 52.4860496
        },
        {
          "longitude": -1.9026915,
          "latitude": 52.4859173
        },
        {
          "longitude": -1.9026915,
          "latitude": 52.4859173
        },
        {
          "longitude": -1.9022061,
          "latitude": 52.4856512
        },
        {
          "longitude": -1.9015865,
          "latitude": 52.4853185
        },
        {
          "longitude": -1.9006321,
          "latitude": 52.4847821
        },
        {
          "longitude": -1.9006321,
          "latitude": 52.4847821
        },
        {
          "longitude": -1.9001466,
          "latitude": 52.4845092
        },
        {
          "longitude": -1.9001466,
          "latitude": 52.4845092
        },
        {
          "longitude": -1.9000268,
          "latitude": 52.4844419
        },
        {
          "longitude": -1.8983388,
          "latitude": 52.4830966
        },
        {
          "longitude": -1.8982603,
          "latitude": 52.4830828
        },
        {
          "longitude": -1.8976585,
          "latitude": 52.4830486
        },
        {
          "longitude": -1.8976063,
          "latitude": 52.483038
        },
        {
          "longitude": -1.8975501,
          "latitude": 52.483025
        },
        {
          "longitude": -1.8971183,
          "latitude": 52.4826903
        },
        {
          "longitude": -1.8970005,
          "latitude": 52.4825538
        },
        {
          "longitude": -1.8969027,
          "latitude": 52.4824411
        },
        {
          "longitude": -1.896864,
          "latitude": 52.4823641
        },
        {
          "longitude": -1.8968404,
          "latitude": 52.4823212
        },
        {
          "longitude": -1.8967787,
          "latitude": 52.4822417
        },
        {
          "longitude": -1.8965233,
          "latitude": 52.4820329
        },
        {
          "longitude": -1.8963826,
          "latitude": 52.4819149
        },
        {
          "longitude": -1.8963826,
          "latitude": 52.4819149
        },
        {
          "longitude": -1.8961779,
          "latitude": 52.4817467
        },
        {
          "longitude": -1.895713,
          "latitude": 52.4813377
        },
        {
          "longitude": -1.8956835,
          "latitude": 52.4812736
        },
        {
          "longitude": -1.8956757,
          "latitude": 52.4812292
        },
        {
          "longitude": -1.8956781,
          "latitude": 52.4811527
        },
        {
          "longitude": -1.8956938,
          "latitude": 52.4811035
        },
        {
          "longitude": -1.895721,
          "latitude": 52.481069
        },
        {
          "longitude": -1.8967177,
          "latitude": 52.4802091
        },
        {
          "longitude": -1.8968394,
          "latitude": 52.480104
        },
        {
          "longitude": -1.8976434,
          "latitude": 52.4794036
        },
        {
          "longitude": -1.8978085,
          "latitude": 52.4791928
        },
        {
          "longitude": -1.8979656,
          "latitude": 52.4790611
        },
        {
          "longitude": -1.8980733,
          "latitude": 52.478985
        },
        {
          "longitude": -1.8982986,
          "latitude": 52.4786141
        },
        {
          "longitude": -1.8984038,
          "latitude": 52.4785694
        },
        {
          "longitude": -1.8984534,
          "latitude": 52.4785543
        },
        {
          "longitude": -1.8985134,
          "latitude": 52.4785473
        },
        {
          "longitude": -1.898905,
          "latitude": 52.4785906
        },
        {
          "longitude": -1.8990706,
          "latitude": 52.4786074
        },
        {
          "longitude": -1.8992366,
          "latitude": 52.4786257
        },
        {
          "longitude": -1.8996191,
          "latitude": 52.4786671
        },
        {
          "longitude": -1.899638,
          "latitude": 52.4786698
        },
        {
          "longitude": -1.8999934,
          "latitude": 52.4787021
        },
        {
          "longitude": -1.9003285,
          "latitude": 52.4787311
        },
        {
          "longitude": -1.9007421,
          "latitude": 52.4787614
        }
      ]
    }
  ]
}